<?xml version="1.0" encoding="UTF-8"?>
<Tokens version="1.0">
	<File path="Classes/CloudWatchDimensionFilter.html">
		
		<Token>
			<TokenIdentifier>//apple_ref/occ/cl/CloudWatchDimensionFilter</TokenIdentifier>
			<Abstract type="html">Dimension Filter</Abstract>
			<DeclaredIn>CloudWatchDimensionFilter.h</DeclaredIn>
			
			<NodeRef refid="136"/>
		</Token>
		
		
		<Token>
			<TokenIdentifier>//apple_ref/occ/instm/CloudWatchDimensionFilter/init</TokenIdentifier>
			<Abstract type="html">Default constructor for a new  object.  Callers should use the
property methods to initialize this object after creating it.</Abstract>
			<DeclaredIn>CloudWatchDimensionFilter.h</DeclaredIn>			
			
			<Declaration>- (id)init</Declaration>
			
			
			<Anchor>//api/name/init</Anchor>
		</Token>
		
		<Token>
			<TokenIdentifier>//apple_ref/occ/instm/CloudWatchDimensionFilter/setName:</TokenIdentifier>
			<Abstract type="html">The dimension name to be matched.
&lt;p&gt;
&lt;b&gt;Constraints:&lt;/b&gt;&lt;br/&gt;
&lt;b&gt;Length: &lt;/b&gt;1 - 255&lt;br/&gt;</Abstract>
			<DeclaredIn>CloudWatchDimensionFilter.h</DeclaredIn>			
			
			<Declaration>@property (nonatomic, retain) NSString *name</Declaration>
			
			
			<Anchor>//api/name/name</Anchor>
		</Token>
		
		<Token>
			<TokenIdentifier>//apple_ref/occ/instp/CloudWatchDimensionFilter/name</TokenIdentifier>
			<Abstract type="html">The dimension name to be matched.
&lt;p&gt;
&lt;b&gt;Constraints:&lt;/b&gt;&lt;br/&gt;
&lt;b&gt;Length: &lt;/b&gt;1 - 255&lt;br/&gt;</Abstract>
			<DeclaredIn>CloudWatchDimensionFilter.h</DeclaredIn>			
			
			<Declaration>@property (nonatomic, retain) NSString *name</Declaration>
			
			
			<Anchor>//api/name/name</Anchor>
		</Token>
		
		<Token>
			<TokenIdentifier>//apple_ref/occ/instm/CloudWatchDimensionFilter/setValue:</TokenIdentifier>
			<Abstract type="html">The value of the dimension to be matched. &lt;note&gt; Specifying a
&lt;code&gt;Name&lt;/code&gt; without specifying a &lt;code&gt;Value&lt;/code&gt; returns all
values associated with that &lt;code&gt;Name&lt;/code&gt;. &lt;/note&gt;
&lt;p&gt;
&lt;b&gt;Constraints:&lt;/b&gt;&lt;br/&gt;
&lt;b&gt;Length: &lt;/b&gt;1 - 255&lt;br/&gt;</Abstract>
			<DeclaredIn>CloudWatchDimensionFilter.h</DeclaredIn>			
			
			<Declaration>@property (nonatomic, retain) NSString *value</Declaration>
			
			
			<Anchor>//api/name/value</Anchor>
		</Token>
		
		<Token>
			<TokenIdentifier>//apple_ref/occ/instp/CloudWatchDimensionFilter/value</TokenIdentifier>
			<Abstract type="html">The value of the dimension to be matched. &lt;note&gt; Specifying a
&lt;code&gt;Name&lt;/code&gt; without specifying a &lt;code&gt;Value&lt;/code&gt; returns all
values associated with that &lt;code&gt;Name&lt;/code&gt;. &lt;/note&gt;
&lt;p&gt;
&lt;b&gt;Constraints:&lt;/b&gt;&lt;br/&gt;
&lt;b&gt;Length: &lt;/b&gt;1 - 255&lt;br/&gt;</Abstract>
			<DeclaredIn>CloudWatchDimensionFilter.h</DeclaredIn>			
			
			<Declaration>@property (nonatomic, retain) NSString *value</Declaration>
			
			
			<Anchor>//api/name/value</Anchor>
		</Token>
		
		<Token>
			<TokenIdentifier>//apple_ref/occ/instm/CloudWatchDimensionFilter/description</TokenIdentifier>
			<Abstract type="html">Returns a string representation of this object; useful for testing and
debugging.</Abstract>
			<DeclaredIn>CloudWatchDimensionFilter.h</DeclaredIn>			
			
			<Declaration>- (NSString *)description</Declaration>
			
			<ReturnValue><Abstract type="html">A string representation of this object.</Abstract></ReturnValue>
			<Anchor>//api/name/description</Anchor>
		</Token>
		
	</File>
</Tokens>